MANIFEST.in
setup.cfg
setup.py
Druid_UI.egg-info/SOURCES.txt
caravel/__init__.py
caravel/ascii_art.py
caravel/config.py
caravel/forms.py
caravel/models.py
caravel/utils.py
caravel/views.py
caravel/viz.py
caravel/bin/caravel
caravel/assets/.babelrc
caravel/assets/.eslintignore
caravel/assets/.eslintrc
caravel/assets/package.json
caravel/assets/webpack.config.js
caravel/assets/images/bubble.png
caravel/assets/images/caravel.jpg
caravel/assets/images/caravel_logo.png
caravel/assets/images/caravel_screenshot.png
caravel/assets/images/cardash.jpg
caravel/assets/images/cloud.png
caravel/assets/images/dash.png
caravel/assets/images/favicon.png
caravel/assets/images/gallery.jpg
caravel/assets/images/loading.gif
caravel/assets/images/noimg.png
caravel/assets/images/penguins.png
caravel/assets/images/serpe.jpg
caravel/assets/images/servers.jpg
caravel/assets/images/slice.jpg
caravel/assets/images/tutorial/add_db.png
caravel/assets/images/tutorial/created.png
caravel/assets/images/tutorial/db_added.png
caravel/assets/images/tutorial/db_menu.png
caravel/assets/images/tutorial/db_plus.png
caravel/assets/images/tutorial/explore.png
caravel/assets/images/tutorial/in_new_dash.png
caravel/assets/images/tutorial/matrix.png
caravel/assets/images/tutorial/new_dash.png
caravel/assets/images/tutorial/pen.png
caravel/assets/images/tutorial/search.png
caravel/assets/images/viz_thumbnails/area.png
caravel/assets/images/viz_thumbnails/bar.png
caravel/assets/images/viz_thumbnails/big_number.png
caravel/assets/images/viz_thumbnails/big_number_total.png
caravel/assets/images/viz_thumbnails/box_plot.png
caravel/assets/images/viz_thumbnails/bubble.png
caravel/assets/images/viz_thumbnails/compare.png
caravel/assets/images/viz_thumbnails/directed_force.png
caravel/assets/images/viz_thumbnails/dist_bar.png
caravel/assets/images/viz_thumbnails/filter_box.png
caravel/assets/images/viz_thumbnails/heatmap.png
caravel/assets/images/viz_thumbnails/iframe.png
caravel/assets/images/viz_thumbnails/line.png
druid_ui.egg-info/PKG-INFO
druid_ui.egg-info/SOURCES.txt
druid_ui.egg-info/dependency_links.txt
druid_ui.egg-info/not-zip-safe
druid_ui.egg-info/requires.txt
druid_ui.egg-info/top_level.txt