Metadata-Version: 1.0
Name: druid-ui
Version: 0.8.9
Summary: A interactive data visualization platform build on SqlAlchemy and druid.io
Home-page: UNKNOWN
Author: abel
Author-email: 156001980@163.com
License: UNKNOWN
Platform: UNKNOWN
